{
  "date": "2026-06-05",
  "prev_date": "2026-06-04",
  "trends": {
    "古风世情": {
      "new_count": 0,
      "dropped_count": 0,
      "new_books": [],
      "dropped_books": [],
      "top_risers": [
        {
          "title": "穿成李治，我和武后he了",
          "change": "+2"
        },
        {
          "title": "某天成为肖家四小姐",
          "change": "+2"
        },
        {
          "title": "将门有朵病娇花",
          "change": "+1"
        }
      ],
      "top_fallers": [
        {
          "title": "剿匪剿到亲闺女，丞相爹爹崩溃了",
          "change": "-4"
        },
        {
          "title": "朕都被掰弯了，你说你是女儿身",
          "change": "-2"
        },
        {
          "title": "我爹又升官了，这次是国丈",
          "change": "-2"
        }
      ],
      "reads_growth": [
        {
          "title": "穿越老朱后宫，我开局冒充长平",
          "growth": "+5000"
        },
        {
          "title": "娇女不争，帝心自倾",
          "growth": "+4000"
        },
        {
          "title": "在二凤身边当伴读的日子",
          "growth": "+3000"
        }
      ],
      "summary": "**🔥 题材趋势** 重生复仇与穿越权谋仍是绝对主流，但“病弱/幼崽”等反套路设定（如《将门有朵病娇花》《本崽说了算》）开始突围，成为差异化竞争点。历史同人（如穿成李治、二凤伴读）热度稳定，提供稳定基本盘。\n**📖 读者偏好** 读者对“强设定+强情感拉扯”组合高度敏感，如《双姝媚骨》的“钓系”和《错嫁渣夫》的“强宠”。简介中明确标注“非爽文”或“无CP”的作品（如《无归朝》）仍能进入前20，说明细分受众忠诚度高。\n**🆕 新上榜作品** 无。\n**📉 掉出榜单** 无。\n**💡 值得关注** 《穿成李治，我和武后he了》排名上升，其“女穿男+姐狗文学”的独特设定在古言中开辟了新鲜赛道，值得观察其长线表现。"
    },
    "科幻末世": {
      "new_count": 1,
      "dropped_count": 1,
      "new_books": [
        "你在做饭呢？我在炼制药剂"
      ],
      "dropped_books": [
        {
          "title": "惊爆星际：她有全能种植系统",
          "intro": "【星际农场+变异植物+基建+无CP+非恶女】 【种田流，辅助种植系统】 这是一个末世普通异能者穿越成星际天才的故事 …… 末世，檀音觉醒了植物异能，种出的作物品质极高 本以为靠着种植异能日子可以好过些"
        }
      ],
      "top_risers": [
        {
          "title": "末世被困男生宿舍被大佬们宠疯",
          "change": "+5"
        },
        {
          "title": "魂穿废土，我绑定了三个老公",
          "change": "+3"
        },
        {
          "title": "公路求生，雪橇犬怎么升级",
          "change": "+2"
        }
      ],
      "top_fallers": [
        {
          "title": "末世降临：我却成了无症状感染者",
          "change": "-7"
        },
        {
          "title": "小队全员兽化，菟丝花夹缝难逃",
          "change": "-1"
        },
        {
          "title": "穿成末世文作精女配后",
          "change": "-1"
        }
      ],
      "reads_growth": [
        {
          "title": "求生游戏：请叫我诚信商人",
          "growth": "+1.1万"
        },
        {
          "title": "哄骗失忆的末世反派后被日日索爱",
          "growth": "+5000"
        },
        {
          "title": "末世被困男生宿舍被大佬们宠疯",
          "growth": "+3000"
        }
      ],
      "summary": "**🔥 题材趋势** 末世求生+异能觉醒是绝对核心，但“非典型”设定正在崛起。如《求生游戏：请叫我诚信商人》的“商人”职业、《公路求生，雪橇犬怎么升级》的“萌宠+基建”，以及《你在做饭呢？我在炼制药剂》的“星际+重生”，都在传统框架内寻求创新。\n**📖 读者偏好** 读者对“强女主+多男主/雄竞”模式（如《末世被抢异能后》《小队全员兽化》）接受度极高，榜单中近半数作品涉及此元素。同时，“无CP”的纯升级爽文（如《领悟空间系法则后我成神了》）也拥有稳定市场，说明读者偏好分化明显。\n**🆕 新上榜作品** 《你在做饭呢？我在炼制药剂》（星际+重生+药剂师），以“重生+职业”的复合设定切入，排名第20，表现稳健。\n**📉 掉出榜单** 《惊爆星际：她有全能种植系统》，或因“星际+种田”题材在末世分类中竞争激烈，被更具新意的作品取代。\n**💡 值得关注** 《末世被困男生宿舍被大佬们宠疯》排名飙升+5，其“美男攻略系统”的设定精准切中“雄竞”热点，是典型的“设定驱动型”爆款潜力股。"
    },
    "游戏体育": {
      "new_count": 2,
      "dropped_count": 2,
      "new_books": [
        "kpl：我想睡觉",
        "侏罗纪求生：百名男神跪求我垂怜"
      ],
      "dropped_books": [
        {
          "title": "我在海洋求生游戏里当钓鱼佬",
          "intro": "【女主无CP+成长型+囤货冒险+钓鱼+海洋求生+微克苏鲁+生存游戏】 苏禾被莫名卷入了一场海洋求生游戏中，每天必须前行系统规定的海里数，她惊讶的发现，自己拥有的钓竿，似乎别人没有……"
        },
        {
          "title": "龙岛异兽：逍遥游",
          "intro": "(私设较多，不喜避雷)(评分刚出) 叶星和他的军团逍遥游是从其他服转到ys005的，身为前服务器的国服第一，来到新的地盘当然要成为第十一名！嗯对，问原因就是前十名当够了。 与阿乐相识后每天更是新鲜事不"
        }
      ],
      "top_risers": [
        {
          "title": "游戏入侵：我靠疯狂打工登顶成神",
          "change": "+11"
        },
        {
          "title": "公路囤货求生：开局一辆三轮车",
          "change": "+1"
        },
        {
          "title": "开局吞噬树召唤玩家横扫废土",
          "change": "+1"
        }
      ],
      "top_fallers": [
        {
          "title": "公路求生：餐车驾到，通通吃饱",
          "change": "-4"
        },
        {
          "title": "列车求生：她最擅长杀人了",
          "change": "-3"
        },
        {
          "title": "开局椰树，求生游戏被奶娃玩崩了",
          "change": "-2"
        }
      ],
      "reads_growth": [
        {
          "title": "游戏入侵：我靠疯狂打工登顶成神",
          "growth": "+6129"
        },
        {
          "title": "求生游戏：我在公路当军火商",
          "growth": "+1046"
        },
        {
          "title": "海岛求生：植灵师大人她只想种田",
          "growth": "+1000"
        }
      ],
      "summary": "**🔥 题材趋势** “全民求生”是绝对统治性题材，其中“公路求生”和“海洋求生”是两大热门子类型。种田、基建、囤货等慢节奏玩法与求生紧张感结合，成为主流叙事模式。电竞题材（如《kpl：我想睡觉》）作为细分赛道，有稳定受众。\n**📖 读者偏好** 读者对“无CP”的强女主爽文（如《海岛求生》《安全屋》）偏好明显，榜单前五中四部为无CP。同时，“女扮男装”的网游文（如《别装了，我的剑宗小姐姐》）和“第四天灾”的幕后流（如《开局吞噬树》）也展现出强劲的差异化吸引力。\n**🆕 新上榜作品** 《kpl：我想睡觉》（电竞+团宠）和《侏罗纪求生：百名男神跪求我垂怜》（求生+万人迷），分别切入电竞和“雄竞”赛道，丰富了榜单题材。\n**📉 掉出榜单** 《我在海洋求生游戏里当钓鱼佬》和《龙岛异兽：逍遥游》，或因题材同质化严重，被更具新意的“公路求生”和“第四天灾”作品取代。\n**💡 值得关注** 《游戏入侵：我靠疯狂打工登顶成神》排名飙升+11，其“打工人”天赋的设定极具网感，将“打工”这一现实元素巧妙融入求生游戏，是“反套路”创新的成功案例。"
    },
    "女频衍生": {
      "new_count": 2,
      "dropped_count": 2,
      "new_books": [
        "我的乖乖快穿到影视剧中名场面",
        "斩神：开局解锁西施"
      ],
      "dropped_books": [
        {
          "title": "综影视：三千世界三千他",
          "intro": "她本是一株佛前梅，听禅百年，互佛而折。 残魂被本体断枝收留，散入三千世界修补自身。 每活一世，便收回一世碎片。集齐之日，便是重生之时。 代价是：每一次穿越，她都会忘却前尘。 而她不知道的是，每个世界都"
        },
        {
          "title": "综影视：有凤来，十里故清欢",
          "intro": "凤清欢，一个倒霉透顶被霉运拖累死的人，可死后才知道，原来自己所承受的霉运都是替旁人承受的！ 罢了罢了，反正已经死了，还能怎么滴？接受现实，领了补偿过日子吧！ 甄嬛传 安陵容 甄嬛传 瓜尔佳文鸳『祺贵人"
        }
      ],
      "top_risers": [
        {
          "title": "穿越之成了贝微微的双生妹妹",
          "change": "+5"
        },
        {
          "title": "这个甄嬛传怎么不一样",
          "change": "+4"
        },
        {
          "title": "斩神：我靠歌声拯救时间之神",
          "change": "+3"
        }
      ],
      "top_fallers": [
        {
          "title": "穿成小燕子：只做乾隆掌中娇宠女",
          "change": "-1"
        },
        {
          "title": "锦叶良缘",
          "change": "-1"
        },
        {
          "title": "黄亦玫重生：这次我选孟宴臣",
          "change": "-1"
        }
      ],
      "reads_growth": [
        {
          "title": "穿越之成了贝微微的双生妹妹",
          "growth": "+2.1万"
        },
        {
          "title": "张桂芬重生：嫁给盛长柏后杀疯了",
          "growth": "+3000"
        },
        {
          "title": "综影视：啊？我要当娘娘了？",
          "growth": "+2000"
        }
      ],
      "summary": "**🔥 题材趋势** 经典IP衍生（《甄嬛传》《还珠格格》《知否》）持续霸榜，但《斩神》等新锐IP快速崛起，形成“老牌经典+新兴IP”双轨并行格局。快穿、综影视题材仍是流量基本盘，系统、幸运值等金手指设定成为标配。\n**📖 读者偏好** 读者对“高爽度+强金手指”的偏好明显，偏爱“大小姐驾到”式碾压爽感与“幸运值点满”的轻松逆袭。同时，对“拆官配”、“拯救意难平”等颠覆性同人创作接受度高，情感向偏好“甜宠+救赎”。\n**🆕 新上榜作品** 《我的乖乖快穿到影视剧中名场面》以“名场面”为钩子，覆盖多个热门IP，降低阅读门槛；《斩神：开局解锁西施》融合“王者系统”与“斩神”IP，尝试跨圈层引流。\n**📉 掉出榜单** 《综影视：三千世界三千他》与《综影视：有凤来，十里故清欢》均为传统综影视快穿，题材同质化严重，缺乏新意，被更具IP辨识度的作品取代。\n**💡 值得关注** 《斩神》IP衍生作品（如《斩神：我靠歌声拯救时间之神》）表现亮眼，显示该IP具备成为女频新热点的潜力，其“拔刀子”、“甜文”的改编方向值得跟进。"
    },
    "玄幻言情": {
      "new_count": 2,
      "dropped_count": 2,
      "new_books": [
        "穿成白虎幼崽，开局剖了男主灵根",
        "小师妹五界第一，天才见她都破防"
      ],
      "dropped_books": [
        {
          "title": "虐完夫君我哭了，他带着崽跑了！",
          "intro": "【本文是虐文，虐心虐身，超虐的那种……罚跪，囚禁，鞭子皆有】 【疯批女魔主，神鸟揣蛋跑！】 七年前，她是仙道天骄，却被挚爱之人亲手推入深渊，堕为魔主！七年后，她携滔天恨意归来，誓要让那高高在上的金乌神"
        },
        {
          "title": "伪装神女后，她成了全皇朝白月光",
          "intro": "修仙救世+开宗立派+无cp+人前显圣 又名《宗门大师姐在凡人界装神女的那些年》 秦扶月金丹碎裂，身死道消。 再次睁眼，她身处一方灾祸不断的凡人界。 成了一个靠着美貌伪装神女的神棍，正是谎言被拆穿，要被"
        }
      ],
      "top_risers": [
        {
          "title": "穿书后我成了修仙界第一咸鱼长老",
          "change": "+6"
        },
        {
          "title": "穿成断供留子食修小摊爆火美利坚",
          "change": "+2"
        },
        {
          "title": "杨戬要疯了：闺女天天想换爹",
          "change": "+2"
        }
      ],
      "top_fallers": [
        {
          "title": "穿越兽世，九阶兽人求契约",
          "change": "-1"
        }
      ],
      "reads_growth": [
        {
          "title": "与清冷少年成亲后才知他是大反派",
          "growth": "+9000"
        },
        {
          "title": "黑化暂停，小师姐我去逮！",
          "growth": "+4000"
        },
        {
          "title": "被夺气运后，我靠双修飞升成神",
          "growth": "+3000"
        }
      ],
      "summary": "**🔥 题材趋势** “穿书+系统+逆袭”是绝对主流，但“训儿/训夫”、“沙雕救赎”等反套路设定开始突围。洪荒、封神等传统仙侠题材与“萌宝”、“团宠”元素结合，形成新看点。\n**📖 读者偏好** 读者对“万人迷”、“雄竞修罗场”和“男全洁”的标签依赖度高，偏好“开局无敌”或“快速成长”的爽感。同时，“沙雕”、“反套路”的轻松风格比传统虐恋更受欢迎。\n**🆕 新上榜作品** 《穿成白虎幼崽，开局剖了男主灵根》以“神兽幼崽+女强”为卖点，主打无CP和反套路；《小师妹五界第一，天才见她都破防》延续“大女主+爽文”模式，强调“天才破防”的爽点。\n**📉 掉出榜单** 《虐完夫君我哭了，他带着崽跑了！》和《伪装神女后，她成了全皇朝白月光》或因“虐文”和“神女”题材热度下降，或因开篇节奏较慢，被更直接、更爽快的作品取代。\n**💡 值得关注** 《剑仙魔尊别舔女主！你妈被气活了》的“训儿”设定和《黑化暂停，小师姐我去逮！》的“沙雕救赎”风格，代表了玄幻言情在“反套路”和“轻喜剧”方向上的新探索，值得持续观察。"
    },
    "种田": {
      "new_count": 3,
      "dropped_count": 3,
      "new_books": [
        "气运被夺致死，醒后我创翻全家！",
        "穿越喜当娘带娃捡漏囤货逃荒",
        "养父母恶毒？不伺候！带灵泉分家"
      ],
      "dropped_books": [
        {
          "title": "刚穿就被卖？我带家人断亲逃荒去",
          "intro": "（评分刚开~会涨的~放心入~） [逃荒+种田+金手指] 末世孤女穿越成农女，爹死娘嫁人，大伯渣，二伯坏，要卖掉她换银子。 江醒表示：小意思，先解决极品伯伯，再利用商城赚钱，带着奶奶和弟弟度过灾年。 战"
        },
        {
          "title": "穿书后，我把虐文男主嘎了",
          "intro": "（男配+科举+基建+无系统+恶毒女配） 现代博士生林青熬夜改论文，一睁眼却成了古代病弱少年林青山。 爹娘刚死，大伯一家就带着人牙子上了门要卖两个妹妹，大的卖去当丫鬟，小的卖去当童养媳。 林青山怒而断亲"
        },
        {
          "title": "萌娃通菜市，古今穿梭顿顿肉",
          "intro": "【古今穿越+萌宝+种田+发家致富+细水长流+温馨日常+无CP+打脸虐渣】 （新书，评分刚出，会涨的~~~） 大周朝闹了百年难得一见的饥荒。 陆绍祖想卖掉五岁的女儿陆桃桃换两斤糙米，妻子傅芸娘拼死反对。"
        }
      ],
      "top_risers": [
        {
          "title": "弃妇带崽逃荒开局一辆电动车",
          "change": "+9"
        },
        {
          "title": "猎户家的罪奴娘子",
          "change": "+4"
        },
        {
          "title": "开局抄家，我带太孙去逃荒",
          "change": "+4"
        }
      ],
      "top_fallers": [
        {
          "title": "荒年不慌：囤百亿物资被糙汉娇宠",
          "change": "-5"
        }
      ],
      "reads_growth": [
        {
          "title": "临水小厨娘",
          "growth": "+1.0万"
        },
        {
          "title": "弃妇带崽逃荒开局一辆电动车",
          "growth": "+1.0万"
        },
        {
          "title": "萌娃携弟闯乱世寻父",
          "growth": "+4000"
        }
      ],
      "summary": "**🔥 题材趋势**  \n逃荒、空间、灵泉、美食、萌宝扎堆，“穿越+金手指（空间/灵泉/异能）+打脸极品+发家致富”成核心公式；先婚后爱、对照组、复仇虐渣等强冲突元素热度不减，日常流与群像文占比提升。\n\n**📖 读者偏好**  \n偏好“爽中带甜”的轻度逆袭：金手指需落地实用（电动车、捡漏系统、灵泉），偏好“带娃/养崽/寻亲”升温亲情线，对大女主无CP或雄竞向包容度高。\n\n**🆕 新上榜作品**  \n- 《气运被夺致死，醒后我创翻全家！》：无CP+气运系统对撞“倒霉蛋逆袭”，切入点新颖。  \n- 《穿越喜当娘带娃捡漏囤货逃荒》：重生儿子+捡漏金手指，亲子协作差异化明显。  \n- 《养父母恶毒？不伺候！带灵泉分家》：末世大佬穿成假千金，空间+复仇条线清晰。\n\n**📉 掉出榜单**  \n《刚穿就被卖？》《穿书后，我把虐文男主嘎了》《萌娃通菜市》均为逃荒/古今穿越类，题材高度同质化且缺乏记忆点；评分刚出未积累口碑，被新鲜设定替代。\n\n**💡 值得关注**  \n- 《市井人家》：无金手指+重组家庭群像，在“爽文”洪流中走反套路日常路线，差异化突围。  \n- 《小吏幺女：我携举家登青云》：以治水为主线，结合科举门庭变迁，跳出纯种田框架，知识流潜力。"
    },
    "年代": {
      "new_count": 2,
      "dropped_count": 2,
      "new_books": [
        "穿越70：原配的美貌不止一点点",
        "快穿：我在年代文里当极品"
      ],
      "dropped_books": [
        {
          "title": "年代恶毒女配：搞钱上学两不误",
          "intro": "（刚开分会涨）时雨雾一朝猝死穿成小说里同名的恶毒女配。贫穷的家，偏心自己的爸妈，瘦小的弟弟和恶毒的她。 在这个遍地是黄金的年代，时雨雾一边上大学一边赚钱，一不小赚的盆满钵满。 本想专心搞事业，谁知那位"
        },
        {
          "title": "真千金小福宝：在北大荒杀疯了",
          "intro": "评分刚出，放心阅读。 1970年，苏沅禾刚出生，就被调换人生。 本该是锦衣玉食的京城豪门千金，却流落到苦寒的北大荒，成了乡下苏家三房的小丫头。 三房父母傲骨强硬，护崽至极，绝不任由家人欺负孩子。 可苏"
        }
      ],
      "top_risers": [
        {
          "title": "绝嗣长官没儿子？小娇妻一胎三宝",
          "change": "+2"
        },
        {
          "title": "穿书香江，我靠写小说发家致富",
          "change": "+2"
        },
        {
          "title": "小保姆和大领导",
          "change": "+2"
        }
      ],
      "top_fallers": [
        {
          "title": "要命！首长的小娇妻夜夜闹离婚",
          "change": "-2"
        },
        {
          "title": "新婚后，禁撩军官变京圈宠妻狂魔",
          "change": "-2"
        }
      ],
      "reads_growth": [
        {
          "title": "绝嗣长官没儿子？小娇妻一胎三宝",
          "growth": "+1.5万"
        },
        {
          "title": "替嫁残疾英雄，婆家宠我青云志",
          "growth": "+1.1万"
        },
        {
          "title": "七零炮灰女配，列车员的悠闲人生",
          "growth": "+9000"
        }
      ],
      "summary": "**🔥 题材趋势** “军婚”、“团宠”、“系统”成为核心卖点，与“替嫁”、“先婚后爱”结合紧密。“丰腴美人”、“小保姆”等标签高频出现，指向特定受众。\n**📖 读者偏好** 读者偏爱“先婚后爱”、“高干甜宠”、“逆袭爽感”，尤其青睐“男强女弱”或“女弱但被宠”的设定。开篇强冲突、快节奏的“契约婚姻”或“穿越觉醒”套路最吃香。\n**🆕 新上榜作品** 《穿越70：原配的美貌不止一点点》以“觉醒+预知灾难”为钩子；《快穿：我在年代文里当极品》主打“快穿+反派主角”，是平台稀缺的变体题材。\n**📉 掉出榜单** 《年代恶毒女配：搞钱上学两不误》与《真千金小福宝：在北大荒杀疯了》掉榜，说明纯“种田/创业”与“福宝萌娃”在当前赛道的竞争力有所下滑。\n**💡 值得关注** “快穿”与“年代”的融合（《快穿：我在年代文里当极品》）是一个新方向；同时，“替嫁”与“好孕/生子系统”结合（《绝嗣长官没儿子？》）的套路仍有极强生命力。"
    },
    "现言脑洞": {
      "new_count": 2,
      "dropped_count": 2,
      "new_books": [
        "穿成游戏文里男主的植物人妹妹",
        "打游戏换美貌，丑胖妹杀疯了"
      ],
      "dropped_books": [
        {
          "title": "绑定带货系统，全网求我别限购",
          "intro": "评分刚出【无cp+大女主】一朝失业，唐小悠绑定了“万界卖货系统”！ 开局即巅峰，售卖九万九一颗的药丸。 直播一开，全网群嘲，路人当她整活，平台拿她当诈骗，可谁也没想到，竟真救回了重病患者。 从全网笑柄"
        },
        {
          "title": "1929在美丽国当神秘大佬",
          "intro": "（评分刚出后续会涨） 【女频爽文+无cp+穿越+系统+创业暴富+背景是上世纪美丽国】 2025年，30岁的杨琳死于空难。 1929年1月，被冻死在纽约街头的10岁的华裔女孩艾琳睁开了眼睛。 “叮，宿主"
        }
      ],
      "top_risers": [
        {
          "title": "反派前妻别死了，回来管好你男人",
          "change": "+3"
        },
        {
          "title": "小说维度晋升，我在天幕当评委",
          "change": "+3"
        },
        {
          "title": "婴语满级，我拿捏全豪门大佬命脉",
          "change": "+1"
        }
      ],
      "top_fallers": [
        {
          "title": "演恋爱脑三年，离婚前夜翻车了",
          "change": "-2"
        },
        {
          "title": "偷听婴儿心声后，豪门为我抢破头",
          "change": "-2"
        },
        {
          "title": "绑定签到系统后，我不知道多快乐",
          "change": "-1"
        }
      ],
      "reads_growth": [
        {
          "title": "穿书兽世：恶雌她终于吃上好的了",
          "growth": "+1.1万"
        },
        {
          "title": "小说维度晋升，我在天幕当评委",
          "growth": "+8000"
        },
        {
          "title": "商K服务员，我靠听金主心声暴富",
          "growth": "+6000"
        }
      ],
      "summary": "**🔥 题材趋势** “穿书+系统”依然是绝对主流，但具体金手指更细化（“变美系统”、“婴语”等）。男频设定（游戏、超凡）的女性向改编成为新增长点。\n**📖 读者偏好** 读者偏好“反差萌”与“逆袭爽感”，如“社恐捞女”、“丑胖女野王”、“两百斤胖子变美女”。同时，“单箭头”或“1V多”的修罗场仍是重要爽点。\n**🆕 新上榜作品** 《穿成游戏文里男主的植物人妹妹》切入“游戏入侵+躺赢”细分赛道，新颖度高；《打游戏换美貌，丑胖妹杀疯了》则精准切中“颜值焦虑+电子竞技”两大痛点。\n**📉 掉出榜单** 《绑定带货系统》与《1929在美丽国当神秘大佬》掉榜，表明“带货/创业”与“异国历史背景”的脑洞题材，在当前竞争激烈的“穿书/系统”红海中获客成本较高。\n**💡 值得关注** 《纯人类在废土被疯狗哨兵强制圈养》的“哨兵向导”设定热度不减，表明特定二次元亚文化圈层正在转化为网文消费力。"
    },
    "宫斗宅斗": {
      "new_count": 1,
      "dropped_count": 1,
      "new_books": [
        "万人迷被所有人觊觎"
      ],
      "dropped_books": [
        {
          "title": "勾了有瘾世子！腰软，也得受着",
          "intro": "【娇软媚香美人vs暴戾疯批有瘾世子爷】 【蓄意勾引+极限拉扯+强取豪夺+黑化宠入骨】 太傅府嫡女沈月妩，死前才知，水匪劫船，她名声尽毁，娘亲吐血惨死，太子妃之位被夺，都是她最宠爱的妹妹沈玉胭做的！ 沈"
        }
      ],
      "top_risers": [
        {
          "title": "一胎双宝，糙汉皇帝夜夜惹火燃尽",
          "change": "+2"
        },
        {
          "title": "大龄通房升职日常",
          "change": "+1"
        },
        {
          "title": "四殿下又在发癫",
          "change": "+1"
        }
      ],
      "top_fallers": [
        {
          "title": "皇兄的金丝雀",
          "change": "-2"
        },
        {
          "title": "替嫁绝嗣太子，我胎胎多宝",
          "change": "-2"
        },
        {
          "title": "状元悔断肠，玄学大佬不好惹",
          "change": "-2"
        }
      ],
      "reads_growth": [
        {
          "title": "四殿下又在发癫",
          "growth": "+6000"
        },
        {
          "title": "二嫁：君夺臣妻！贵妃冠宠后宫",
          "growth": "+6000"
        },
        {
          "title": "兄长，你敢娶女主我就跟山匪私奔",
          "growth": "+5000"
        }
      ],
      "summary": "**🔥 题材趋势**  \n当前“强取豪夺+通房/妾室”设定扎堆，穿越、重生、系统金手指高频出现，病弱/疯批男主与“胎胎多宝”元素成标配，同质化竞争加剧。\n\n**📖 读者偏好**  \n甜宠爽文主导，偏好“上位者低头”“打脸逆袭”的强情绪拉扯，金手指偏好系统、变美、多胎等即时反馈型设定。\n\n**🆕 新上榜作品**  \n《万人迷被所有人觊觎》以快穿+万人迷+强取豪夺切入，多世界设定提供差异化新鲜感，但需警惕题材内卷。\n\n**📉 掉出榜单**  \n《勾了有瘾世子！腰软，也得受着》因“娇软美人×疯批世子”套路过于常见，且缺乏新金手指或反转设定，被同质化作品挤出。\n\n**💡 值得关注**  \n《四殿下又在发癫》以“无cp+摆烂皇子”反套路叙事，跳出宫斗宅斗常规框架，差异化明显；《皇家街溜子》用古今结合崽崽视角制造轻松笑点，适合下沉市场。"
    },
    "悬疑脑洞": {
      "new_count": 1,
      "dropped_count": 1,
      "new_books": [
        "什么变态，那是我老公"
      ],
      "dropped_books": [
        {
          "title": "刑侦甜妹，在变态修罗场杀疯了",
          "intro": "苏杳，江城刑侦支队出了名的“倒霉社畜”、“外卖毁灭者”、“混吃等死第一名”。 直到震惊全国的“全员恶人碎尸案”发生，老刑警们一筹莫展。 苏杳咬着煎饼果子路过，只扫了一眼现场：“别找了，作案工具在死者情"
        }
      ],
      "top_risers": [
        {
          "title": "盗墓笔记：原来是故人没死",
          "change": "+1"
        }
      ],
      "top_fallers": [
        {
          "title": "漂亮小可怜在暗黑童话被疯狂觊觎",
          "change": "-2"
        },
        {
          "title": "盗墓：开局给黑瞎子算命",
          "change": "-2"
        },
        {
          "title": "盗墓：战五渣？她可是满级辅助",
          "change": "-2"
        }
      ],
      "reads_growth": [
        {
          "title": "盗墓：你们偷我家小麒麟？",
          "growth": "+1.5万"
        },
        {
          "title": "盗墓：开局给小花推销乾坤袋",
          "growth": "+1.2万"
        },
        {
          "title": "盗墓笔记：原来是故人没死",
          "growth": "+3000"
        }
      ],
      "summary": "**🔥 题材趋势** 《盗墓笔记》同人继续统治榜单，占比高达50%，但玩法开始分化，从单纯的“万人迷”向“系统流”、“身份误会”及“非人类马甲”等细分方向探索。恐怖、无限流题材也占据一席之地，并尝试与弹幕、游戏等元素结合。  \n**📖 读者偏好** 读者对强设定、标签明确的“轻松向”、“搞笑向”作品接受度高，偏好“万人迷”、“脑补”、“团宠”等元素，且对系统、重生等金手指有明确需求。同时，对评分和排名变动敏感。  \n**🆕 新上榜作品** 《什么变态，那是我老公》以“弹幕+悬疑”为题材，讲述女主发现丈夫是变态杀人狂的故事，将弹幕文化与悬疑惊悚融合，开辟了新的赛道。  \n**📉 掉出榜单** 《刑侦甜妹，在变态修罗场杀疯了》掉出榜单，其“刑侦+甜妹”的设定在悬疑脑洞榜竞争中略显疲软，未能持续吸引读者。  \n**💡 值得关注** 《什么变态，那是我老公》的弹幕元素创新值得注意，证明了“弹幕+悬疑”的融合题材具备潜力；《盗墓：别不拿NPC当回事》以反套路“粽子”视角切入，提供了差异化内容。"
    },
    "古言脑洞": {
      "new_count": 1,
      "dropped_count": 1,
      "new_books": [
        "战神流放，我带空间来撑场"
      ],
      "dropped_books": [
        {
          "title": "糖霜谱：我在古代当情感调解师",
          "intro": "猝死+穿越+系统+和离+追妻=全员火葬场？ 现代王牌调解师穿成古代狗血小说家，开局一无所有？ 不！她有系统！ 调解一桩姻缘，系统奖励一包跳跳糖？ 治愈一个冰山，阎王直接以身相许！ 打脸一个反派，皇帝亲"
        }
      ],
      "top_risers": [
        {
          "title": "病弱太子李承乾，重生团宠万人迷",
          "change": "+5"
        },
        {
          "title": "我沙场点兵，我爹官场争宠",
          "change": "+2"
        },
        {
          "title": "大明：重生成朱雄英的伴生神兽",
          "change": "+2"
        }
      ],
      "top_fallers": [
        {
          "title": "抄家流放？战王妃携空间先搬为敬",
          "change": "-3"
        },
        {
          "title": "绑定宠妃系统后我当皇帝了",
          "change": "-2"
        },
        {
          "title": "万人迷病美人她总是高不可攀",
          "change": "-2"
        }
      ],
      "reads_growth": [
        {
          "title": "我沙场点兵，我爹官场争宠",
          "growth": "+8000"
        },
        {
          "title": "我在乱世靠换装系统装神女",
          "growth": "+6000"
        },
        {
          "title": "满宫不孕，唯我三年抱俩！",
          "growth": "+6000"
        }
      ],
      "summary": "**🔥 题材趋势** “系统”与“创业”结合为最大爽点，如《换装系统》的装神女、《生子系统》的三年抱俩。同时，“带崽/婴语”和“女强/双强”题材持续火热，满足读者对“团宠”和“逆袭”的双重需求。  \n**📖 读者偏好** 读者偏好“爽点密集”、“团宠”、“无CP”或“双洁”的设定，对“白月光回归”、“装逼打脸”、“父子情/萌宝”等元素接受度高。同时，对“流放”、“抄家”等经典冲突设定有稳定需求。  \n**🆕 新上榜作品** 《战神流放，我带空间来撑场》延续了“穿越+空间+逆袭”的经典套路，将军夫人蒙冤流放的主线，是当前榜单中少见的“女强+爽文”题材。  \n**📉 掉出榜单** 《糖霜谱：我在古代当情感调解师》掉出榜单，其“情感调解”的设定在追求强冲突、快节奏的古言脑洞区显得冲突不足。  \n**💡 值得关注** 《我沙场点兵，我爹官场争宠》以“母女双系统”的独特设定排名上升，开创了亲子携手搞事业的新模式；《我真的只想躺平，却被系统挖了坟》的“小僵尸”+“团宠”设定，为古言题材提供了新灵感。"
    },
    "快穿": {
      "new_count": 1,
      "dropped_count": 1,
      "new_books": [
        "快穿：万人迷她又茶又钓"
      ],
      "dropped_books": [
        {
          "title": "快穿：绿茶女配她手段了得",
          "intro": "（1v1）温旎作为快穿局的新手员工，被组织分配到了女配组。 女配组的任务很简单，就是扮演剧情里的女配，按剧本走完该走的剧情就行。 穿成太子那个爱慕虚荣的救命恩人，温旎等着被揭穿后扫地出门，结果太子把她"
        }
      ],
      "top_risers": [
        {
          "title": "快穿：疯批男主们的心机女友",
          "change": "+3"
        },
        {
          "title": "漂亮女配怎么成了男主的心肝宝贝",
          "change": "+2"
        },
        {
          "title": "快穿：恶毒女配靠攻略抢回男主",
          "change": "+2"
        }
      ],
      "top_fallers": [
        {
          "title": "快穿：天生好孕被绝嗣大佬宠上天",
          "change": "-2"
        },
        {
          "title": "快穿：枝枝挂满蜜桃香",
          "change": "-2"
        },
        {
          "title": "快穿：钓系魅魔的顶级软饭法则",
          "change": "-2"
        }
      ],
      "reads_growth": [
        {
          "title": "厨神快穿，我在各个世界当大厨",
          "growth": "+1.3万"
        },
        {
          "title": "快穿：吾之第一女技能生效",
          "growth": "+1.2万"
        },
        {
          "title": "快穿：疯批男主们的心机女友",
          "growth": "+5000"
        }
      ],
      "summary": "**🔥 题材趋势**  \n当前快穿新书榜以“病娇强制爱”“攻略男主”“万人迷修罗场”为核心题材，高频元素包括系统、双洁、1v1/1vN、甜宠。生子/孕、男视角攻略等细分设定开始扎堆，同质化竞争加剧。\n\n**📖 读者偏好**  \n读者偏好甜宠+爽感，偏好“被宠”“被攻略”的被动型女主，金手指以系统、万人迷体质"
    },
    "青春甜宠": {
      "new_count": 1,
      "dropped_count": 1,
      "new_books": [
        "我，怂且恶毒"
      ],
      "dropped_books": [
        {
          "title": "不装了！我全家都是疯批大反派",
          "intro": "【我家户口本＝通缉令合集】 　　祝愿因为一纸亲子鉴定被踹出豪门，转头就被亲爹妈接回了一座小岛。 　　她狂喜，终于不用受气了！ 　　亲爹妈是渔民，淳朴善良，靠海吃饭。 　　祝愿感动得嗷嗷哭——多好的人啊"
        }
      ],
      "top_risers": [
        {
          "title": "我刻薄不是装的",
          "change": "+3"
        },
        {
          "title": "F4里最病弱的那个，被团宠了",
          "change": "+1"
        },
        {
          "title": "给十四岁的她五千万",
          "change": "+1"
        }
      ],
      "top_fallers": [
        {
          "title": "她比南风更自由",
          "change": "-2"
        },
        {
          "title": "盛夏青苹果",
          "change": "-2"
        },
        {
          "title": "【普女】：我怎么会喜欢她！",
          "change": "-2"
        }
      ],
      "reads_growth": [
        {
          "title": "大小姐雇我替她和太子爷网恋",
          "growth": "+2.1万"
        },
        {
          "title": "F4里最病弱的那个，被团宠了",
          "growth": "+1.4万"
        },
        {
          "title": "病弱美人只想搞学习续命",
          "growth": "+4000"
        }
      ],
      "summary": "**🔥 题材趋势** 网恋/替身文学成为绝对流量密码，榜首84万在读领跑。穿书、重生框架与“恶女”“普女”人设结合趋势明显，旨在通过身份错位制造戏剧冲突和代入感。\n**📖 读者偏好** 读者明确追求“双洁”“甜宠”“无虐”“轻松日常”的情绪价值。对“病弱”“团宠”“系统”等设定接受度高，期待高糖与反差人设（如学霸与校霸），对纯现实向慢热题材的反馈较为温和。\n**🆕 新上榜作品** 《我，怂且恶毒》（4.4万在读）融合重生、系统、恶毒女配感化设定，以强烈的反套路人设（女主曾阉割男主）和新颖的“怂且恶毒”的定位吸引眼球，获得市场认可。\n**📉 掉出榜单** 《不装了！我全家都是疯批大反派》题材（全家皆反派、通缉令合集）相对小众，在竞争激烈的甜宠赛道中，未能持续吸引追求轻快甜爽的核心读者。\n**💡 值得关注** 《我刻薄不是装的》排名上升（+3），其“恶女万人迷”“雄竞”风格证明，在主流甜宠外，带有鲜明性格缺陷与修罗场元素的“坏女孩”设定正形成明确的小众突围路径。"
    },
    "星光璀璨": {
      "new_count": 3,
      "dropped_count": 3,
      "new_books": [
        "淡颜女主播：神豪团的掌心宠",
        "榜一跑路，但主播是脸蛋天才",
        "不装了摊牌了，神豪她都要"
      ],
      "dropped_books": [
        {
          "title": "恋综被黑，我反手打脸爆红全网",
          "intro": "评分会涨‖【双洁+娱乐圈+甜爽文+豪门世家+青梅竹马+双强】 舒姿，全网公认的“小三”。 被网暴的第二天，经纪人把她塞进了一档恋综，节目组搞事情，把她的“前CP”和“情敌”全请来了。 舒姿看着镜头，面"
        },
        {
          "title": "天然萌主播竟是钓系",
          "intro": "【直播+神豪哥姐+天然撩主播+正文不在一起＋撒娇+女主中心】 [番茄里挑八卦直播间] 挑八卦指着大屏幕上对乐鱼助人直播间所有大哥的性格分析。 “...所以，综上所述，你们觉得小鱼家有几个‘哥’粉，‘爹"
        },
        {
          "title": "影后守寡五年，战神旅长回来了",
          "intro": "惊鸿一遇，她以为只是擦肩而过的陌生人。 横城片场，她从威压上失足坠落。千钧一发之际，一身戎装的他伸手稳稳接住。 他是红色高干出身的特种兵中队长，军中传奇；她只是娱乐圈最底层摸爬滚打的小群演。云泥之别，"
        }
      ],
      "top_risers": [
        {
          "title": "女穿男，万人迷从颜值拉满开始",
          "change": "+4"
        },
        {
          "title": "女尊之驯服顶流：追夫火葬场",
          "change": "+3"
        },
        {
          "title": "直播：被豪门找回的我成了万人迷",
          "change": "+2"
        }
      ],
      "top_fallers": [
        {
          "title": "什么？八卦主播横扫颜值区了！",
          "change": "-1"
        },
        {
          "title": "陆地：官宣恋情后竟无一人震惊",
          "change": "-1"
        },
        {
          "title": "颜值女主播：我才是神豪真心肝",
          "change": "-1"
        }
      ],
      "reads_growth": [
        {
          "title": "被太子爷背出剧组那天，京圈炸了",
          "growth": "+5000"
        },
        {
          "title": "女穿男，万人迷从颜值拉满开始",
          "growth": "+3000"
        },
        {
          "title": "直播：被豪门找回的我成了万人迷",
          "growth": "+2000"
        }
      ],
      "summary": "**🔥 题材趋势** 娱乐圈与直播文高度融合，成为绝对主导。围绕“主播-神豪”互动衍生的文种（如恶毒前爱播、女主播万人迷）占据半壁江山，显著特征是“神豪”“百万”“团宠”高频出现。\n**📖 读者偏好** 读者偏好“爽感”优先，追求“神颜”“万人迷”“无CP”或“1VN”的设定，厌倦被虐。对“重生复仇”“女强回归”叙事以及突入其来的反转（如赞助商是我妈、老板是影帝）充满热情。\n**🆕 新上榜作品** 《淡颜女主播》《榜一跑路》《不装了摊牌了》三部新作均围绕直播与神豪展开，强化了“神豪团”“团宠”“淡颜反杀”等细分元素，显示市场正深挖直播生态下的情感与经济博弈。\n**📉 掉出榜单** 《恋综被黑》《天然萌主播》《影后守寡》的掉榜，说明在黑马文持续冲榜下，“恋综”题材热度有所冷却，纯粹“守寡”虐恋在追求爽感的“星光”赛道不易保持高位。\n**💡 值得关注** 《女穿男，万人迷从颜值拉满开始》排名上升（+4），凭借“女穿男+娱乐圈+红包群”的多重金手指叠加和新鲜设定，成功在高度同质化的直播文中开辟出差异化的高关注度。"
    },
    "女频悬疑": {
      "new_count": 3,
      "dropped_count": 3,
      "new_books": [
        "盗墓：她自深渊来",
        "盗墓：一言不合她就反",
        "穿越八零，我能闻到凶手的味道"
      ],
      "dropped_books": [
        {
          "title": "偷我照片网恋？反手送室友入狱",
          "intro": "前世社恐窝囊死的林晚意，一睁眼穿越成江大第一校花。 刚醒来，就撞见胖丑室友王莉莉拿她的私照给三个男人发嗲：\"哥哥~人家想你了~\" 一查聊天记录——好家伙！国服野王、京圈太子爷、科技新贵，三个顶级大佬被"
        },
        {
          "title": "穿成虞姬去盗墓",
          "intro": "余姬穿越王者大陆变成了虞姬，通过努力刷怪、偷塔攒钱买了虞姬的三个皮肤“霸王别姬”、“云霓雀翎”、“神鉴启示录”，就不幸的又穿了，这次居然是盗墓笔记！！！"
        },
        {
          "title": "她闻得出来",
          "intro": "我是林砚，一名法医，懂中医，会辨毒。 见过最温柔的妻子，被枕边人藏进地下室。 见过最善良的老人，被护工悄悄换掉汤药。 见过最无辜的女孩，被霸凌逼到绝路。 每一具尸体，都藏着没说出口的真相。 每一个案件"
        }
      ],
      "top_risers": [
        {
          "title": "综盗墓：男神排排坐",
          "change": "+5"
        },
        {
          "title": "别关灯，这个厉鬼他暗恋我七年",
          "change": "+3"
        },
        {
          "title": "盗墓：我在盗笔杀穿主线",
          "change": "+2"
        }
      ],
      "top_fallers": [
        {
          "title": "和张起灵分手后，他要炸了青铜门",
          "change": "-8"
        },
        {
          "title": "穿成诡异贵族学院F5恶毒前女友",
          "change": "-3"
        },
        {
          "title": "盗墓：把我睡了的债主又活了",
          "change": "-1"
        }
      ],
      "reads_growth": [
        {
          "title": "综盗墓：男神排排坐",
          "growth": "+6000"
        },
        {
          "title": "盗笔我在沙海当歌后",
          "growth": "+3000"
        },
        {
          "title": "90小片警：惊！又在案发现场",
          "growth": "+3000"
        }
      ],
      "summary": "**🔥 题材趋势** “盗墓”同人（尤其是《盗墓笔记》）几乎统治榜单，占比过半。纯原创悬疑则偏向“特工穿越”“入殓师通灵”等带有特殊设定或职业背景的叙事，寻求在传统刑侦外的新意。\n**📖 读者偏好** 读者并不强求硬核推理，而是偏爱在悬疑背景下的“互动”与“团宠”，如守墓兽被小哥投喂、厉鬼暗恋、前辈关照。对“万人迷”“修罗场”等情节在悬疑框架下的嫁接接受度极高。\n**🆕 新上榜作品** 《盗墓：她自深渊来》（1.8万在读）以“异世界深渊领主”闯入盗笔世界的极高战力+双强设定，为同人文赛道提供了全新的主角定位和叙事角度，丰富了题材想象力。\n**📉 掉出榜单** 《偷我照片网恋》《穿成虞姬去盗墓》《她闻得出来》掉榜，显示在盗墓同人强势霸榜下，缺乏IP基础或创新融合不足的原创悬疑，在流量争夺中相对处于劣势。\n**💡 值得关注** 《综盗墓：男神排排坐》排名上升（+5），其“每个故事换主角”的形式创新和“攻略不同男神”的明确指向，精准满足了读者在同一世界观下体验多元爱情互动的需求。"
    },
    "职场婚恋": {
      "new_count": 2,
      "dropped_count": 2,
      "new_books": [
        "闪婚刑警老公，陆队人前请装不熟",
        "夜幕下的女大学生"
      ],
      "dropped_books": [
        {
          "title": "七年无声",
          "intro": "七年前，她误会了他，连夜离开，一句话没留。 七年后，搬进新公寓的第一天，隔壁开门，是他。 后来她才知道，他选这套房，不是偶然。 两个人都用七年学会了独当一面，却始终没学会跟对方说清楚一句话。 所有的误"
        },
        {
          "title": "我被老公骗去缅北",
          "intro": "【分刚出，非爽文，强逻辑】 写下这段经历，只为撕开境外那些专门针对女性的骗局。 从写字楼里一场看似偶然的邂逅开始， 一张吞噬数百人的罪恶大网，正悄然收紧，将无数女孩诱骗至缅北园区。 2018年，我被丈"
        }
      ],
      "top_risers": [
        {
          "title": "七年难孕，再婚后一胎双宝",
          "change": "+6"
        },
        {
          "title": "杀出缅北，她登顶金三角",
          "change": "+2"
        },
        {
          "title": "双京记",
          "change": "+2"
        }
      ],
      "top_fallers": [
        {
          "title": "新娘换人后，周队长夜里亲得好凶",
          "change": "-1"
        },
        {
          "title": "离婚后，周律彻底失控了",
          "change": "-1"
        }
      ],
      "reads_growth": [
        {
          "title": "他的生理性喜欢",
          "growth": "+1.3万"
        },
        {
          "title": "穿成恶毒女配和落魄男主拼婚养娃",
          "growth": "+5000"
        },
        {
          "title": "七年难孕，再婚后一胎双宝",
          "growth": "+2000"
        }
      ],
      "summary": "**🔥 题材趋势** “先婚后爱/闪婚”仍是绝对主流，但内核已从纯甜宠转向“联手对抗奇葩家人”的现实向冲突。婆媳矛盾、离婚重生、中年困境等强情绪议题成为新爆点，如《奇葩婆婆》《40岁离婚的女人》均表现强劲。\n**📖 读者偏好** 读者对“生理性喜欢”和“爹系宠溺”的细分需求旺盛，偏好高浓度情感拉扯与“打直球”互动。同时，对“无CP独美”和“大女主逆袭”的接受度显著提升，如《双京记》《杀出缅北》排名上升。\n**🆕 新上榜作品** 《闪婚刑警老公，陆队人前请装不熟》融合“刑侦+先婚后爱”，以职业设定增加新鲜感；《夜幕下的女大学生》聚焦底层女性群像，题材差异化明显。\n**📉 掉出榜单** 《七年无声》和《我被老公骗去缅北》掉榜，前者或因“久别重逢”套路化，后者或因“缅北”题材热度回落，且非爽文定位在职场婚恋赛道略显沉重。\n**💡 值得关注** 《双京记》作为“无CP+种田养娃”作品排名上升，验证了“去恋爱化”叙事的市场潜力，或为平台开辟新细分赛道提供参考。"
    },
    "豪门总裁": {
      "new_count": 2,
      "dropped_count": 2,
      "new_books": [
        "宝贝乖，让我亲一下",
        "救命！景少又吃醋了"
      ],
      "dropped_books": [
        {
          "title": "完蛋，穿成女二她妈，和男主备孕",
          "intro": "【丰腴绿茶人妻×爱喝茶古板太子爷+暧昧拉扯+女主最美+年龄差9岁】 苏糯顶级美颜，一觉醒来，她却穿成了恶女重生小说中被利用到死的女二，的妈！ 书中，她的女儿被重生的女主当枪使，什么脏活累活全给她干，最"
        },
        {
          "title": "沈总，你的恋爱脑娇妻不要你喽",
          "intro": "【女主看似娇妻，实则800个心眼子】 【男主看似薄情，实则妻奴恋爱脑】 【追妻+双洁】 人人都知道江虞爱惨了沈承晏。 结婚五年，她对沈承晏百依百顺，言听计从。 她是恋爱脑，是冷脸洗内裤的娇妻。 她这辈"
        }
      ],
      "top_risers": [
        {
          "title": "弟弟们好凶！！！明明我才是大哥",
          "change": "+5"
        },
        {
          "title": "被强制爱生下的儿子穿过来了",
          "change": "+2"
        },
        {
          "title": "小叔囚宠：我成了盛总的笼中雀",
          "change": "+2"
        }
      ],
      "top_fallers": [
        {
          "title": "禁止侵入",
          "change": "-2"
        },
        {
          "title": "京圈小公主抢我男友，我当她继母",
          "change": "-1"
        },
        {
          "title": "许我明珠",
          "change": "-1"
        }
      ],
      "reads_growth": [
        {
          "title": "弟弟们好凶！！！明明我才是大哥",
          "growth": "+3.6万"
        },
        {
          "title": "冒名顶替真千金后，嫁入了豪门",
          "growth": "+2.6万"
        },
        {
          "title": "豪门小娇妻超甜！大佬夜夜亲红温",
          "growth": "+2.0万"
        }
      ],
      "summary": "**🔥 题材趋势**  \n穿书/重生女配逆袭为核心设定，高频搭配“强制爱”“先婚后爱”“年龄差”及“双洁”标签。假千金、金丝雀、恶毒女配改命模板扎堆，同质化竞争加剧。\n\n**📖 读者偏好**  \n甜宠向为主，偏好“上位者为爱低头”的极致反差与轻微虐感（火葬场），金手指集中于穿书预知、重生弥补遗憾，追求情绪释放与爽感。\n\n**🆕 新上榜作品**  \n- 《宝贝乖，让我亲一下》：软萌乖乖女×疯批病娇年上男，强化“养成年下”与强占有欲格差。  \n- 《救命！景少又吃醋了》：先身后爱+疯批控制欲男主，以直白欲望钩子吸引下沉读者。\n\n**📉 掉出榜单**  \n- 《完蛋，穿成女二她妈，和男主备孕》：人妻+年龄差设定虽新奇，但伦理尺度未转化足够留存。  \n- 《沈总，你的恋爱脑娇妻不要你喽》：“娇妻翻身”套路饱和，缺乏差异化记忆点。\n\n**💡 值得关注**  \n- 《弟弟们好凶！！！"
    },
    "民国言情": {
      "new_count": 2,
      "dropped_count": 2,
      "new_books": [
        "谍战，我是鬼子女贵族",
        "陈皮阿四之多情种"
      ],
      "dropped_books": [
        {
          "title": "穿成系统后，太姥带我搬空了法租",
          "intro": "【穿越民国+1932+爱国情怀+空间+虐渣+资本家大小姐VS来自后世的曾孙女+八零那本书前卷】 　　小翎子穿越到三十年代沪市，意外成了太姥的系统，只是，她才蛊惑太姥搬空渣男家的仓库，就被太姥带着搬空了"
        },
        {
          "title": "奉陪【民国】",
          "intro": "宋临夏初见裴定澜，她是北上寻亲的孤女，他是四九城里有名的家族败类，不肖子孙。 　　她差点命丧黄泉，他出手相救。 　　二见裴定澜，她是抵死不嫁的宋家三小姐，他是来看热闹的裴九爷。 　　她孤立无援，他拾步"
        }
      ],
      "top_risers": [
        {
          "title": "军阀养女：狼崽子的白月光是姐姐",
          "change": "+1"
        },
        {
          "title": "捂不热的军婚，她不要了",
          "change": "+1"
        }
      ],
      "top_fallers": [
        {
          "title": "人间正道是沧桑：四十年来家国",
          "change": "-1"
        },
        {
          "title": "潜伏：风雨故人来",
          "change": "-1"
        },
        {
          "title": "清冷四小姐：良辰美景奈何天",
          "change": "-1"
        }
      ],
      "reads_growth": [
        {
          "title": "穿越民国，获得每日签到系统",
          "growth": "+2000"
        },
        {
          "title": "玉佩通两界，儿童特战小队",
          "growth": "+1000"
        },
        {
          "title": "酒后错撩杀猪匠",
          "growth": "+1000"
        }
      ],
      "summary": "**🔥 题材趋势**  \n“军阀/少帅”与“强制爱/闪婚”组合持续霸榜，同时“谍战+系统/穿越”成为第二大热门赛道。高频元素包括：穿越、系统签到、先婚后爱、囚宠、养成，同质化倾向明显。\n\n**📖 读者偏好**  \n读者偏好“强占有欲+甜宠”的爽感叙事，金手指偏好系统签到、空间、异能等即时变现型设定，对虐恋接受度低，更倾向“虐中带甜”或“女强逆袭”。\n\n**🆕 新上榜作品**  \n- 《谍战，我是鬼子女贵族》：谍战+鬼族身份，差异化设定吸引猎奇读者。  \n- 《陈皮阿四之多情种》：老九门同人小甜文，粉丝向精准，私设丰富。\n\n**📉 掉出榜单**  \n- 《穿成系统后，太姥带我搬空了法租》：系统+空间+爱国题材饱和，缺乏新意。  \n- 《奉陪【民国】》："
    }
  }
}